sample/__init__.py
sample/package_data.dat
sample/simple.py
aginfrastructure-0.0.0.dist-info/LICENSE
aginfrastructure-0.0.0.dist-info/LICENSE-AGiXT
aginfrastructure-0.0.0.dist-info/METADATA
aginfrastructure-0.0.0.dist-info/WHEEL
aginfrastructure-0.0.0.dist-info/entry_points.txt
aginfrastructure-0.0.0.dist-info/top_level.txt
aginfrastructure-0.0.0.dist-info/RECORD
